popxf/tools/__init__.py
popxf/tools/_version.py
popxf/tools/formatting.py
popxf/tools/parser.py
popxf/tools/polynomial.py
popxf/tools/typedmapping.py
popxf/tools/bin/__init__.py
popxf/tools/bin/popxf_validate.py
popxf_tools-0.0.1.dist-info/licenses/LICENSE
popxf_tools-0.0.1.dist-info/METADATA
popxf_tools-0.0.1.dist-info/WHEEL
popxf_tools-0.0.1.dist-info/entry_points.txt
popxf_tools-0.0.1.dist-info/top_level.txt
popxf_tools-0.0.1.dist-info/RECORD
