Metadata-Version: 2.4
Name: popxf-tools
Version: 0.0.1
Summary: Package for various POPxf tools
Author-email: Ken Mimasu <ken.mimasu@soton.ac.uk>, Aleks Smolkovič <aleks.smolkovic@ijs.si>, Peter Stangl <peter.stangl@cern.ch>
License: MIT
Requires-Python: >=3.8
License-File: LICENSE
Requires-Dist: jsonschema
Requires-Dist: numpy
Requires-Dist: popxf-validator==0.0.1
Dynamic: license-file
